bgm_labour/__init__.py
bgm_labour/__main__.py
bgm_toolkit_labour-0.1.22.dist-info/licenses/LICENSE
bgm_toolkit_labour-0.1.22.dist-info/METADATA
bgm_toolkit_labour-0.1.22.dist-info/WHEEL
bgm_toolkit_labour-0.1.22.dist-info/entry_points.txt
bgm_toolkit_labour-0.1.22.dist-info/top_level.txt
bgm_toolkit_labour-0.1.22.dist-info/RECORD
