Metadata-Version: 2.4
Name: bgm-toolkit-labour
Version: 0.1.22
Summary: Labour add-ons for BGM Toolkit
Requires-Python: >=3.9
License-File: LICENSE
Requires-Dist: bgm-toolkit-pro>=0.2.14
Dynamic: license-file
